{
  "code": "clubWorldCup2025",
  "group": [
    {
      "groupName": "A",
      "teamOrder": [
        "Palmeiras (BRA)",
        "Inter Miami (USA)",
        "Porto (POR)",
        "Al Ahly (EGY)"
      ]
    },
    {
      "groupName": "B",
      "teamOrder": [
        "Paris Saint-Germain (FRA)",
        "Botafogo (BRA)",
        "Atletico Madrid (ESP)",
        "Seattle Sounders (USA)"
      ]
    },
    {
      "groupName": "C",
      "teamOrder": [
        "Benfica (POR)",
        "Bayern Munich (GER)",
        "Boca Juniors (ARG)",
        "Auckland City (NZL)"
      ]
    },
    {
      "groupName": "D",
      "teamOrder": [
        "Flamengo (BRA)",
        "Chelsea (ENG)",
        "Esperance (TUN)",
        "LAFC (USA)"
      ]
    },
    {
      "groupName": "E",
      "teamOrder": [
        "Internazionale (ITA)",
        "Monterrey (MEX)",
        "River Plate (ARG)",
        "Urawa Red Diamonds (JAP)"
      ]
    },
    {
      "groupName": "F",
      "teamOrder": [
        "Borussia Dortmund (GER)",
        "Fluminense (BRA)",
        "Mamelodi Sundowns (RSA)",
        "Ulsan HD (KOR)"
      ]
    },
    {
      "groupName": "G",
      "teamOrder": [
        "Manchester City (ENG)",
        "Juventus (ITA)",
        "Al Ain (UAE)",
        "Wydad (MOR)"
      ]
    },
    {
      "groupName": "H",
      "teamOrder": [
        "Real Madrid (ESP)",
        "Al Hilal (SAU)",
        "Salzburg (AUT)",
        "Pachuca (MEX)"
      ]
    }
  ],
  "playoff": [
    {
      "round": 1,
      "teams": [
        "Palmeiras (BRA)",
        "Inter Miami (USA)",
        "Paris Saint-Germain (FRA)",
        "Botafogo (BRA)",
        "Benfica (POR)",
        "Bayern Munich (GER)",
        "Flamengo (BRA)",
        "Chelsea (ENG)",
        "Internazionale (ITA)",
        "Monterrey (MEX)",
        "Borussia Dortmund (GER)",
        "Fluminense (BRA)",
        "Juventus (ITA)",
        "Manchester City (ENG)",
        "Real Madrid (ESP)",
        "Al Hilal (SAU)"
      ],
      "points": 2
    },
    {
      "round": 2,
      "teams": [
        "Palmeiras (BRA)",
        "Chelsea (ENG)",
        "Paris Saint-Germain (FRA)",
        "Bayern Munich (GER)",
        "Fluminense (BRA)",
        "Al Hilal (SAU)",
        "Real Madrid (ESP)",
        "Borussia Dortmund (GER)"
      ],
      "points": 4
    },
    {
      "round": 3,
      "teams": [
        "Fluminense (BRA)",
        "Chelsea (ENG)",
        "Paris Saint-Germain (FRA)",
        "Real Madrid (ESP)"
      ],
      "points": 8
    },
    {
      "round": 4,
      "teams": ["Chelsea (ENG)", "Paris Saint-Germain (FRA)"],
      "points": 16
    }
  ],
  "misc": {
    "winner": "Chelsea (ENG)",
    "discipline": ["Chelsea (ENG)"],
    "topScorer": ["Real Madrid (ESP)"]
  },
  "potentials": {},
  "leaders": [
    {
      "key": "discipline",
      "label": "Worst Discipline",
      "leaders": [
        { "team": "Chelsea (ENG)", "value": "17 Yellow Cards, 1 Red Card" }
      ]
    },
    {
      "key": "topScorer",
      "label": "Top Goalscorer",
      "leaders": [
        {
          "team": "Real Madrid (ESP)",
          "player": "Gonzalo Garcia",
          "value": "4 Goals, 1 Assist",
          "eliminated": true
        }
      ]
    }
  ]
}
